[{"id":1,"first_name":"Almeta","last_name":"Mowne","email":"amowne0@purevolume.com","date_of_birth":"1981-10-11T10:09:56Z","age":58,"country":"Afghanistan","phone":"257-255-6098"},
{"id":2,"first_name":"Una","last_name":"Prichard","email":"uprichard1@scientificamerican.com","date_of_birth":"2011-03-02T01:08:03Z","age":18,"country":"South Africa","phone":"305-415-0693"},
{"id":3,"first_name":"Pet","last_name":"Fookes","email":"pfookes2@hostgator.com","date_of_birth":"1995-03-20T19:11:34Z","age":51,"country":"Portugal","phone":"296-617-7162"},
{"id":4,"first_name":"Greer","last_name":"Jozefowicz","email":"gjozefowicz3@imdb.com","date_of_birth":"1998-10-30T08:20:24Z","age":26,"country":"North Korea","phone":"911-604-3696"},
{"id":5,"first_name":"Joanne","last_name":"Sutherel","email":"jsutherel4@skype.com","date_of_birth":"1995-02-17T02:19:30Z","age":32,"country":"Slovenia","phone":"242-944-1394"},
{"id":6,"first_name":"Hymie","last_name":"Berrane","email":"hberrane5@constantcontact.com","date_of_birth":"2021-04-21T02:51:04Z","age":45,"country":"Georgia","phone":"392-454-5819"},
{"id":7,"first_name":"Matthieu","last_name":"Yerrall","email":"myerrall6@arizona.edu","date_of_birth":"2014-01-03T03:10:18Z","age":56,"country":"Philippines","phone":"982-452-4517"},
{"id":8,"first_name":"Wilie","last_name":"Player","email":"wplayer7@acquirethisname.com","date_of_birth":"2009-05-05T10:51:45Z","age":35,"country":"Portugal","phone":"758-745-8381"},
{"id":9,"first_name":"Rafaelia","last_name":"Vanichev","email":"rvanichev8@mashable.com","date_of_birth":"2003-10-13T21:56:39Z","age":47,"country":"Indonesia","phone":"464-495-7207"},
{"id":10,"first_name":"Madalena","last_name":"Pinkie","email":"mpinkie9@indiegogo.com","date_of_birth":"1979-08-25T03:57:28Z","age":26,"country":"East Timor","phone":"838-489-7685"},
{"id":11,"first_name":"Salaidh","last_name":"Mann","email":"smanna@opera.com","date_of_birth":"2019-03-12T02:08:27Z","age":21,"country":"El Salvador","phone":"111-600-9971"},
{"id":12,"first_name":"Weider","last_name":"Sawden","email":"wsawdenb@bravesites.com","date_of_birth":"1987-12-14T15:40:01Z","age":25,"country":"Indonesia","phone":"990-721-2966"},
{"id":13,"first_name":"Berry","last_name":"Critchlow","email":"bcritchlowc@youku.com","date_of_birth":"1993-12-29T00:02:48Z","age":35,"country":"Russia","phone":"411-975-2035"},
{"id":14,"first_name":"Melisande","last_name":"Drinkhall","email":"mdrinkhalld@auda.org.au","date_of_birth":"1991-05-07T13:37:44Z","age":44,"country":"Indonesia","phone":"856-561-1232"},
{"id":15,"first_name":"Nolly","last_name":"Goade","email":"ngoadee@technorati.com","date_of_birth":"1981-12-31T19:43:05Z","age":30,"country":"Sweden","phone":"369-324-1786"},
{"id":16,"first_name":"Jilli","last_name":"Saylor","email":"jsaylorf@cisco.com","date_of_birth":"1974-02-25T18:35:11Z","age":21,"country":"Palestinian Territory","phone":"562-511-8334"},
{"id":17,"first_name":"Dulce","last_name":"Robley","email":"drobleyg@microsoft.com","date_of_birth":"1991-01-03T18:13:52Z","age":41,"country":"Brazil","phone":"414-632-8688"},
{"id":18,"first_name":"Joelly","last_name":"Durston","email":"jdurstonh@samsung.com","date_of_birth":"2002-04-16T13:57:10Z","age":45,"country":"Portugal","phone":"792-266-4715"},
{"id":19,"first_name":"Guglielma","last_name":"Bickardike","email":"gbickardikei@usatoday.com","date_of_birth":"2002-12-28T17:08:46Z","age":22,"country":"Sweden","phone":"677-184-2783"},
{"id":20,"first_name":"Pen","last_name":"Rigard","email":"prigardj@addtoany.com","date_of_birth":"1987-12-28T11:14:37Z","age":50,"country":"Bolivia","phone":"764-823-3779"},
{"id":21,"first_name":"Byrann","last_name":"Mathewson","email":"bmathewsonk@163.com","date_of_birth":"1982-06-15T05:40:48Z","age":35,"country":"Palestinian Territory","phone":"425-415-7452"},
{"id":22,"first_name":"Aundrea","last_name":"Saffran","email":"asaffranl@about.me","date_of_birth":"2019-05-25T23:19:21Z","age":51,"country":"Indonesia","phone":"496-555-7069"},
{"id":23,"first_name":"North","last_name":"Baumber","email":"nbaumberm@toplist.cz","date_of_birth":"2001-03-13T11:08:23Z","age":19,"country":"Greece","phone":"780-761-5662"},
{"id":24,"first_name":"Gregg","last_name":"Paulin","email":"gpaulinn@globo.com","date_of_birth":"1991-10-26T00:17:10Z","age":37,"country":"Czech Republic","phone":"842-467-3651"},
{"id":25,"first_name":"Edvard","last_name":"Minney","email":"eminneyo@ameblo.jp","date_of_birth":"2000-12-21T08:21:46Z","age":23,"country":"Syria","phone":"983-456-8478"},
{"id":26,"first_name":"Porty","last_name":"Syde","email":"psydep@nytimes.com","date_of_birth":"2020-01-16T20:03:02Z","age":48,"country":"Sweden","phone":"264-323-1898"},
{"id":27,"first_name":"Madison","last_name":"Sinkins","email":"msinkinsq@nytimes.com","date_of_birth":"1971-03-24T14:43:25Z","age":26,"country":"France","phone":"350-314-4892"},
{"id":28,"first_name":"Kaleb","last_name":"Borgne","email":"kborgner@china.com.cn","date_of_birth":"1976-03-23T08:48:15Z","age":45,"country":"United States","phone":"602-927-4787"},
{"id":29,"first_name":"Avram","last_name":"Rummer","email":"arummers@blogtalkradio.com","date_of_birth":"2017-09-21T18:58:59Z","age":26,"country":"Argentina","phone":"699-349-5627"},
{"id":30,"first_name":"Karil","last_name":"Britland","email":"kbritlandt@java.com","date_of_birth":"2019-05-16T19:24:14Z","age":33,"country":"Luxembourg","phone":"522-632-7090"},
{"id":31,"first_name":"Dael","last_name":"Sweatman","email":"dsweatmanu@myspace.com","date_of_birth":"2001-12-25T16:54:15Z","age":51,"country":"Portugal","phone":"780-151-2976"},
{"id":32,"first_name":"Kizzee","last_name":"Meyrick","email":"kmeyrickv@typepad.com","date_of_birth":"2022-03-02T07:23:12Z","age":36,"country":"Brazil","phone":"144-181-1826"},
{"id":33,"first_name":"Josy","last_name":"Treverton","email":"jtrevertonw@slideshare.net","date_of_birth":"1993-06-05T10:36:00Z","age":50,"country":"China","phone":"641-190-0229"},
{"id":34,"first_name":"Adelina","last_name":"Windibank","email":"awindibankx@cpanel.net","date_of_birth":"1983-03-31T08:19:34Z","age":45,"country":"Nigeria","phone":"434-378-1552"},
{"id":35,"first_name":"Alyosha","last_name":"Gronauer","email":"agronauery@liveinternet.ru","date_of_birth":"1977-08-15T15:17:53Z","age":35,"country":"Portugal","phone":"978-761-0519"},
{"id":36,"first_name":"Jeanine","last_name":"McGriffin","email":"jmcgriffinz@admin.ch","date_of_birth":"1973-12-24T13:06:10Z","age":45,"country":"Indonesia","phone":"998-727-4179"},
{"id":37,"first_name":"Miller","last_name":"Houlridge","email":"mhoulridge10@purevolume.com","date_of_birth":"2003-03-11T17:15:21Z","age":53,"country":"Poland","phone":"421-602-7932"},
{"id":38,"first_name":"Annmarie","last_name":"Picton","email":"apicton11@google.it","date_of_birth":"1990-02-25T14:55:03Z","age":44,"country":"Colombia","phone":"254-544-9184"},
{"id":39,"first_name":"Quinlan","last_name":"Symms","email":"qsymms12@storify.com","date_of_birth":"2007-08-24T16:32:24Z","age":22,"country":"Russia","phone":"819-662-5472"},
{"id":40,"first_name":"Torr","last_name":"McAuley","email":"tmcauley13@umich.edu","date_of_birth":"1979-10-10T08:53:43Z","age":40,"country":"Indonesia","phone":"706-485-3581"},
{"id":41,"first_name":"Linn","last_name":"Ruilton","email":"lruilton14@nps.gov","date_of_birth":"2019-07-06T17:23:43Z","age":20,"country":"Indonesia","phone":"884-726-0149"},
{"id":42,"first_name":"Collette","last_name":"Grigson","email":"cgrigson15@guardian.co.uk","date_of_birth":"2017-04-07T18:43:31Z","age":21,"country":"Indonesia","phone":"612-123-7053"},
{"id":43,"first_name":"Stanly","last_name":"Leipnik","email":"sleipnik16@1688.com","date_of_birth":"1987-12-30T22:06:27Z","age":55,"country":"Indonesia","phone":"279-649-3397"},
{"id":44,"first_name":"Asher","last_name":"Penney","email":"apenney17@xinhuanet.com","date_of_birth":"2018-05-02T20:32:30Z","age":28,"country":"Costa Rica","phone":"112-666-2621"},
{"id":45,"first_name":"Rayna","last_name":"Biskupiak","email":"rbiskupiak18@constantcontact.com","date_of_birth":"2004-11-18T17:46:22Z","age":43,"country":"Indonesia","phone":"545-551-0546"},
{"id":46,"first_name":"Guthrie","last_name":"Carlyle","email":"gcarlyle19@surveymonkey.com","date_of_birth":"1981-07-14T00:09:34Z","age":50,"country":"Fiji","phone":"921-467-0681"},
{"id":47,"first_name":"Anthea","last_name":"Cheine","email":"acheine1a@bloglovin.com","date_of_birth":"2009-09-24T15:00:31Z","age":50,"country":"China","phone":"968-647-0318"},
{"id":48,"first_name":"Aubrette","last_name":"Tomley","email":"atomley1b@rediff.com","date_of_birth":"1971-08-09T22:01:05Z","age":21,"country":"Jordan","phone":"243-160-8459"},
{"id":49,"first_name":"Tobit","last_name":"Caccavella","email":"tcaccavella1c@infoseek.co.jp","date_of_birth":"1991-01-12T16:04:32Z","age":30,"country":"Armenia","phone":"940-329-7265"},
{"id":50,"first_name":"Timmie","last_name":"Weatherup","email":"tweatherup1d@ustream.tv","date_of_birth":"1990-08-31T10:57:45Z","age":36,"country":"China","phone":"982-259-7206"},
{"id":51,"first_name":"Stepha","last_name":"McCane","email":"smccane1e@miitbeian.gov.cn","date_of_birth":"1982-10-12T15:38:06Z","age":58,"country":"Venezuela","phone":"696-496-6824"},
{"id":52,"first_name":"Gearalt","last_name":"Rockwill","email":"grockwill1f@ft.com","date_of_birth":"1988-09-29T01:46:41Z","age":44,"country":"France","phone":"390-857-4839"},
{"id":53,"first_name":"Ignatius","last_name":"Ipsly","email":"iipsly1g@soup.io","date_of_birth":"1987-10-19T09:22:33Z","age":19,"country":"Indonesia","phone":"368-721-2242"},
{"id":54,"first_name":"Christan","last_name":"Scorthorne","email":"cscorthorne1h@technorati.com","date_of_birth":"2020-04-01T01:34:33Z","age":43,"country":"Cyprus","phone":"447-353-1694"},
{"id":55,"first_name":"Darryl","last_name":"Cowpe","email":"dcowpe1i@biblegateway.com","date_of_birth":"1988-07-03T07:58:01Z","age":19,"country":"Vietnam","phone":"899-488-9157"},
{"id":56,"first_name":"Holly","last_name":"Scotchmore","email":"hscotchmore1j@shareasale.com","date_of_birth":"1984-07-17T02:48:29Z","age":58,"country":"Japan","phone":"800-853-0286"},
{"id":57,"first_name":"Helyn","last_name":"Copson","email":"hcopson1k@forbes.com","date_of_birth":"1999-01-25T06:36:38Z","age":31,"country":"United States","phone":"701-875-5661"},
{"id":58,"first_name":"Shina","last_name":"Leeman","email":"sleeman1l@va.gov","date_of_birth":"2003-08-12T16:09:36Z","age":22,"country":"China","phone":"103-159-9249"},
{"id":59,"first_name":"Mattias","last_name":"Berringer","email":"mberringer1m@tuttocitta.it","date_of_birth":"1979-03-28T16:34:50Z","age":36,"country":"Indonesia","phone":"644-656-1384"},
{"id":60,"first_name":"Allys","last_name":"Dearn","email":"adearn1n@about.com","date_of_birth":"2001-05-29T14:08:45Z","age":37,"country":"Indonesia","phone":"122-453-5299"},
{"id":61,"first_name":"Brett","last_name":"Pashby","email":"bpashby1o@delicious.com","date_of_birth":"1982-08-04T00:30:26Z","age":53,"country":"China","phone":"476-644-3782"},
{"id":62,"first_name":"Haskel","last_name":"Ash","email":"hash1p@nature.com","date_of_birth":"1970-11-16T23:49:35Z","age":46,"country":"Russia","phone":"312-976-5255"},
{"id":63,"first_name":"Gorden","last_name":"Charker","email":"gcharker1q@ebay.co.uk","date_of_birth":"2014-12-29T11:06:28Z","age":47,"country":"Uganda","phone":"160-623-6419"},
{"id":64,"first_name":"Tiffani","last_name":"Macartney","email":"tmacartney1r@wisc.edu","date_of_birth":"1989-02-11T19:55:07Z","age":26,"country":"Philippines","phone":"339-804-4604"},
{"id":65,"first_name":"Ted","last_name":"Hesbrook","email":"thesbrook1s@studiopress.com","date_of_birth":"1975-11-21T10:13:16Z","age":28,"country":"Russia","phone":"397-804-8307"},
{"id":66,"first_name":"Reube","last_name":"McKiddin","email":"rmckiddin1t@fda.gov","date_of_birth":"2002-06-10T07:17:19Z","age":30,"country":"Czech Republic","phone":"744-812-8886"},
{"id":67,"first_name":"Wilone","last_name":"Woolsey","email":"wwoolsey1u@github.io","date_of_birth":"1993-02-09T00:04:31Z","age":19,"country":"Argentina","phone":"514-410-4700"},
{"id":68,"first_name":"Barris","last_name":"Krollmann","email":"bkrollmann1v@adobe.com","date_of_birth":"2005-05-19T19:02:17Z","age":46,"country":"Indonesia","phone":"918-140-8080"},
{"id":69,"first_name":"Humfrey","last_name":"Dixcey","email":"hdixcey1w@hibu.com","date_of_birth":"2015-02-01T04:57:55Z","age":27,"country":"Brazil","phone":"284-263-3409"},
{"id":70,"first_name":"Tye","last_name":"Emmott","email":"temmott1x@home.pl","date_of_birth":"1979-12-08T18:57:24Z","age":34,"country":"Armenia","phone":"304-967-0222"},
{"id":71,"first_name":"Cecilla","last_name":"Juggings","email":"cjuggings1y@friendfeed.com","date_of_birth":"2003-06-03T01:39:38Z","age":35,"country":"Slovenia","phone":"560-117-4968"},
{"id":72,"first_name":"Dacy","last_name":"Oleszkiewicz","email":"doleszkiewicz1z@apple.com","date_of_birth":"2015-10-16T04:43:59Z","age":54,"country":"Indonesia","phone":"505-491-1303"},
{"id":73,"first_name":"Leela","last_name":"Gerriets","email":"lgerriets20@github.com","date_of_birth":"1987-02-05T16:12:51Z","age":21,"country":"Pakistan","phone":"728-668-8426"},
{"id":74,"first_name":"Welby","last_name":"Quinton","email":"wquinton21@delicious.com","date_of_birth":"2022-12-27T20:01:27Z","age":18,"country":"China","phone":"485-533-2285"},
{"id":75,"first_name":"Marina","last_name":"Younghusband","email":"myounghusband22@mysql.com","date_of_birth":"2015-10-04T22:55:07Z","age":40,"country":"Canada","phone":"786-448-2059"},
{"id":76,"first_name":"Megen","last_name":"Whitcombe","email":"mwhitcombe23@alexa.com","date_of_birth":"2021-05-20T14:51:59Z","age":25,"country":"Russia","phone":"685-585-9866"},
{"id":77,"first_name":"Troy","last_name":"Rodolico","email":"trodolico24@elegantthemes.com","date_of_birth":"2018-11-27T23:48:40Z","age":23,"country":"Libya","phone":"626-846-7953"},
{"id":78,"first_name":"Violante","last_name":"Davidow","email":"vdavidow25@bluehost.com","date_of_birth":"2010-01-18T11:54:07Z","age":18,"country":"Guatemala","phone":"550-215-2565"},
{"id":79,"first_name":"Drucill","last_name":"Taffs","email":"dtaffs26@nba.com","date_of_birth":"1994-04-06T16:53:40Z","age":25,"country":"China","phone":"628-682-2169"},
{"id":80,"first_name":"Bobbye","last_name":"Sigert","email":"bsigert27@sfgate.com","date_of_birth":"1998-05-05T15:50:17Z","age":37,"country":"Philippines","phone":"779-718-4926"},
{"id":81,"first_name":"Walther","last_name":"Ketch","email":"wketch28@arstechnica.com","date_of_birth":"1993-09-18T13:34:42Z","age":50,"country":"Finland","phone":"811-224-9179"},
{"id":82,"first_name":"Cobby","last_name":"Penhaligon","email":"cpenhaligon29@nsw.gov.au","date_of_birth":"2007-09-14T12:00:56Z","age":35,"country":"Russia","phone":"974-323-0950"},
{"id":83,"first_name":"Gretel","last_name":"Gilman","email":"ggilman2a@theatlantic.com","date_of_birth":"1997-04-27T11:01:09Z","age":24,"country":"Bosnia and Herzegovina","phone":"563-924-1813"},
{"id":84,"first_name":"Reynard","last_name":"O'Fallon","email":"rofallon2b@livejournal.com","date_of_birth":"1979-06-10T04:07:12Z","age":21,"country":"China","phone":"669-797-3288"},
{"id":85,"first_name":"Gerrard","last_name":"Whild","email":"gwhild2c@ovh.net","date_of_birth":"2004-06-29T18:06:49Z","age":48,"country":"Nicaragua","phone":"993-832-6473"},
{"id":86,"first_name":"Carolyn","last_name":"Gunney","email":"cgunney2d@gmpg.org","date_of_birth":"2001-01-24T04:22:37Z","age":36,"country":"Sweden","phone":"605-342-0364"},
{"id":87,"first_name":"Avery","last_name":"Kunzelmann","email":"akunzelmann2e@merriam-webster.com","date_of_birth":"2011-11-12T13:55:25Z","age":32,"country":"Armenia","phone":"978-551-9605"},
{"id":88,"first_name":"Tod","last_name":"Gindghill","email":"tgindghill2f@princeton.edu","date_of_birth":"1990-02-24T13:48:02Z","age":27,"country":"Iran","phone":"742-515-7633"},
{"id":89,"first_name":"Ab","last_name":"Gauson","email":"agauson2g@smh.com.au","date_of_birth":"2021-07-20T04:40:52Z","age":43,"country":"Russia","phone":"444-468-7055"},
{"id":90,"first_name":"Flora","last_name":"Ingre","email":"fingre2h@boston.com","date_of_birth":"2017-07-21T10:30:30Z","age":52,"country":"Guinea","phone":"768-780-1530"},
{"id":91,"first_name":"Joyann","last_name":"Haizelden","email":"jhaizelden2i@nbcnews.com","date_of_birth":"2019-10-23T22:43:45Z","age":41,"country":"Poland","phone":"974-311-7944"},
{"id":92,"first_name":"Bartholomeus","last_name":"Tassel","email":"btassel2j@amazon.co.jp","date_of_birth":"2004-04-02T15:39:38Z","age":22,"country":"Ecuador","phone":"503-781-7991"},
{"id":93,"first_name":"Inessa","last_name":"Arend","email":"iarend2k@ning.com","date_of_birth":"1979-09-27T08:06:29Z","age":50,"country":"South Africa","phone":"608-729-1977"},
{"id":94,"first_name":"Stavro","last_name":"Parrish","email":"sparrish2l@utexas.edu","date_of_birth":"2011-10-12T01:43:40Z","age":26,"country":"Indonesia","phone":"717-887-5589"},
{"id":95,"first_name":"Heath","last_name":"Kleyn","email":"hkleyn2m@so-net.ne.jp","date_of_birth":"1976-02-02T23:25:10Z","age":47,"country":"Mozambique","phone":"789-724-0349"},
{"id":96,"first_name":"Allyce","last_name":"Sankey","email":"asankey2n@istockphoto.com","date_of_birth":"2009-12-07T14:59:54Z","age":31,"country":"China","phone":"691-377-5025"},
{"id":97,"first_name":"Merell","last_name":"Bullan","email":"mbullan2o@flickr.com","date_of_birth":"1975-10-18T10:53:47Z","age":20,"country":"Democratic Republic of the Congo","phone":"175-259-7176"},
{"id":98,"first_name":"Justino","last_name":"Geater","email":"jgeater2p@miitbeian.gov.cn","date_of_birth":"2016-07-30T02:34:27Z","age":56,"country":"China","phone":"412-463-9469"},
{"id":99,"first_name":"Phylis","last_name":"Kubecka","email":"pkubecka2q@feedburner.com","date_of_birth":"1985-09-30T08:40:27Z","age":40,"country":"Portugal","phone":"869-394-0912"},
{"id":100,"first_name":"Krissie","last_name":"Yorath","email":"kyorath2r@who.int","date_of_birth":"1978-12-25T08:37:38Z","age":19,"country":"China","phone":"972-985-7388"},
{"id":101,"first_name":"Elianore","last_name":"Brogiotti","email":"ebrogiotti2s@tinyurl.com","date_of_birth":"1984-10-10T18:08:03Z","age":36,"country":"Norway","phone":"327-909-3314"},
{"id":102,"first_name":"Elston","last_name":"Scholefield","email":"escholefield2t@joomla.org","date_of_birth":"2009-11-16T22:43:12Z","age":49,"country":"Libya","phone":"796-287-1787"},
{"id":103,"first_name":"Shanda","last_name":"St. Louis","email":"sstlouis2u@dell.com","date_of_birth":"2006-06-26T19:43:13Z","age":27,"country":"United States","phone":"303-294-6160"},
{"id":104,"first_name":"Kaitlin","last_name":"Rewan","email":"krewan2v@yale.edu","date_of_birth":"2020-05-26T03:49:25Z","age":50,"country":"Argentina","phone":"489-992-3504"},
{"id":105,"first_name":"Florella","last_name":"Fearne","email":"ffearne2w@taobao.com","date_of_birth":"1985-06-17T00:42:36Z","age":22,"country":"Brazil","phone":"869-915-3484"},
{"id":106,"first_name":"Knox","last_name":"Cottage","email":"kcottage2x@lulu.com","date_of_birth":"2006-02-11T02:06:11Z","age":25,"country":"Uzbekistan","phone":"227-510-8768"},
{"id":107,"first_name":"Valentino","last_name":"Logesdale","email":"vlogesdale2y@people.com.cn","date_of_birth":"1974-04-07T09:28:39Z","age":39,"country":"France","phone":"290-207-2803"},
{"id":108,"first_name":"Nikolia","last_name":"Gouda","email":"ngouda2z@indiegogo.com","date_of_birth":"1977-05-20T05:19:00Z","age":48,"country":"China","phone":"497-514-0944"},
{"id":109,"first_name":"Daren","last_name":"Beauchamp","email":"dbeauchamp30@rakuten.co.jp","date_of_birth":"2004-01-19T09:00:34Z","age":20,"country":"Czech Republic","phone":"443-766-8561"},
{"id":110,"first_name":"Kennett","last_name":"Alexandrescu","email":"kalexandrescu31@independent.co.uk","date_of_birth":"2011-01-05T15:38:46Z","age":19,"country":"United States","phone":"571-834-2991"},
{"id":111,"first_name":"Lorie","last_name":"Jarred","email":"ljarred32@amazonaws.com","date_of_birth":"1973-11-13T11:17:11Z","age":38,"country":"Brazil","phone":"557-908-2945"},
{"id":112,"first_name":"Nicolea","last_name":"Brereton","email":"nbrereton33@cbc.ca","date_of_birth":"2000-10-13T07:40:03Z","age":22,"country":"Argentina","phone":"453-225-7646"},
{"id":113,"first_name":"Kati","last_name":"Smalls","email":"ksmalls34@cbc.ca","date_of_birth":"1987-04-13T21:13:35Z","age":29,"country":"South Africa","phone":"248-879-1052"},
{"id":114,"first_name":"Ibbie","last_name":"Blaze","email":"iblaze35@hud.gov","date_of_birth":"1991-11-10T20:04:55Z","age":26,"country":"Indonesia","phone":"820-633-9090"},
{"id":115,"first_name":"Filide","last_name":"Aviss","email":"faviss36@linkedin.com","date_of_birth":"1976-03-13T06:29:38Z","age":35,"country":"Poland","phone":"660-691-5135"},
{"id":116,"first_name":"Ban","last_name":"Sowood","email":"bsowood37@tuttocitta.it","date_of_birth":"1974-01-08T18:31:23Z","age":36,"country":"Colombia","phone":"203-813-2499"},
{"id":117,"first_name":"Nelly","last_name":"Rickword","email":"nrickword38@thetimes.co.uk","date_of_birth":"1973-07-08T20:51:27Z","age":41,"country":"China","phone":"335-379-6324"},
{"id":118,"first_name":"Dedra","last_name":"Gabby","email":"dgabby39@berkeley.edu","date_of_birth":"2015-06-27T21:23:44Z","age":20,"country":"Dominican Republic","phone":"634-236-8209"},
{"id":119,"first_name":"Noelyn","last_name":"Cowerd","email":"ncowerd3a@wordpress.com","date_of_birth":"1971-11-16T22:23:49Z","age":31,"country":"Peru","phone":"879-954-4164"},
{"id":120,"first_name":"Darius","last_name":"Meatyard","email":"dmeatyard3b@prweb.com","date_of_birth":"2012-03-06T07:01:55Z","age":44,"country":"Brazil","phone":"510-967-4337"},
{"id":121,"first_name":"Chrystel","last_name":"Alan","email":"calan3c@geocities.com","date_of_birth":"1973-10-15T02:42:36Z","age":47,"country":"France","phone":"746-689-1229"},
{"id":122,"first_name":"Rachel","last_name":"Moughton","email":"rmoughton3d@nature.com","date_of_birth":"1972-08-14T10:35:37Z","age":39,"country":"Russia","phone":"243-521-3216"},
{"id":123,"first_name":"Petronille","last_name":"Ivashkov","email":"pivashkov3e@xinhuanet.com","date_of_birth":"1992-08-31T01:03:38Z","age":47,"country":"Indonesia","phone":"554-995-8273"},
{"id":124,"first_name":"Osbourn","last_name":"Nolda","email":"onolda3f@networksolutions.com","date_of_birth":"1974-11-23T04:10:31Z","age":57,"country":"Russia","phone":"525-917-1009"},
{"id":125,"first_name":"Sybilla","last_name":"Gorringe","email":"sgorringe3g@cmu.edu","date_of_birth":"1981-08-01T07:52:27Z","age":51,"country":"Indonesia","phone":"780-126-7394"},
{"id":126,"first_name":"Priscella","last_name":"Stuehmeier","email":"pstuehmeier3h@earthlink.net","date_of_birth":"1997-09-03T02:28:34Z","age":45,"country":"Japan","phone":"195-791-4961"},
{"id":127,"first_name":"Kaleb","last_name":"Ledwitch","email":"kledwitch3i@theguardian.com","date_of_birth":"2019-03-15T12:51:52Z","age":46,"country":"Indonesia","phone":"106-473-2826"},
{"id":128,"first_name":"Hobard","last_name":"Bland","email":"hbland3j@cornell.edu","date_of_birth":"1972-05-20T02:40:37Z","age":36,"country":"France","phone":"151-770-4437"},
{"id":129,"first_name":"Murry","last_name":"Paridge","email":"mparidge3k@ycombinator.com","date_of_birth":"2014-04-27T13:40:25Z","age":56,"country":"Brazil","phone":"405-727-4424"},
{"id":130,"first_name":"Brian","last_name":"Dod","email":"bdod3l@discuz.net","date_of_birth":"1979-05-13T10:33:01Z","age":58,"country":"China","phone":"718-181-0583"},
{"id":131,"first_name":"Kyrstin","last_name":"Godsmark","email":"kgodsmark3m@wikia.com","date_of_birth":"1987-03-24T01:14:45Z","age":48,"country":"Thailand","phone":"388-419-3803"},
{"id":132,"first_name":"Corrine","last_name":"Kondratyuk","email":"ckondratyuk3n@narod.ru","date_of_birth":"1990-07-09T23:47:12Z","age":28,"country":"American Samoa","phone":"955-609-7292"},
{"id":133,"first_name":"Brigitta","last_name":"Crumbleholme","email":"bcrumbleholme3o@bizjournals.com","date_of_birth":"1985-03-25T04:55:32Z","age":26,"country":"Philippines","phone":"800-792-9788"},
{"id":134,"first_name":"Marj","last_name":"Kinavan","email":"mkinavan3p@marketwatch.com","date_of_birth":"1976-06-04T05:51:12Z","age":30,"country":"Russia","phone":"699-954-9630"},
{"id":135,"first_name":"Biddy","last_name":"Ryam","email":"bryam3q@businessinsider.com","date_of_birth":"1980-12-27T22:34:51Z","age":22,"country":"Philippines","phone":"940-851-3045"},
{"id":136,"first_name":"Yasmin","last_name":"Ellingsworth","email":"yellingsworth3r@dmoz.org","date_of_birth":"1988-01-27T22:37:15Z","age":55,"country":"Ukraine","phone":"617-623-3167"},
{"id":137,"first_name":"Elsy","last_name":"Walby","email":"ewalby3s@netscape.com","date_of_birth":"1987-06-02T10:13:00Z","age":57,"country":"China","phone":"613-988-4346"},
{"id":138,"first_name":"Kirby","last_name":"Mennithorp","email":"kmennithorp3t@youtu.be","date_of_birth":"1976-03-01T16:44:50Z","age":42,"country":"Pakistan","phone":"264-240-0726"},
{"id":139,"first_name":"Annalee","last_name":"MacCole","email":"amaccole3u@51.la","date_of_birth":"2021-01-05T13:10:46Z","age":54,"country":"Indonesia","phone":"569-589-5857"},
{"id":140,"first_name":"Fay","last_name":"Getley","email":"fgetley3v@springer.com","date_of_birth":"1996-09-06T04:14:39Z","age":26,"country":"China","phone":"639-743-3126"},
{"id":141,"first_name":"Nikita","last_name":"Pioli","email":"npioli3w@wired.com","date_of_birth":"2002-05-03T01:47:25Z","age":34,"country":"China","phone":"194-297-4001"},
{"id":142,"first_name":"Stafani","last_name":"Brassill","email":"sbrassill3x@tmall.com","date_of_birth":"1986-05-09T00:07:55Z","age":29,"country":"Latvia","phone":"443-453-8613"},
{"id":143,"first_name":"Clyde","last_name":"Guerrieri","email":"cguerrieri3y@usgs.gov","date_of_birth":"2014-06-21T18:18:40Z","age":48,"country":"Colombia","phone":"656-898-6275"},
{"id":144,"first_name":"Parry","last_name":"Binstead","email":"pbinstead3z@t-online.de","date_of_birth":"1993-03-13T19:26:12Z","age":21,"country":"Ukraine","phone":"325-861-8827"},
{"id":145,"first_name":"Al","last_name":"Pettet","email":"apettet40@comsenz.com","date_of_birth":"2017-04-03T05:27:24Z","age":27,"country":"Philippines","phone":"470-281-0911"},
{"id":146,"first_name":"Teresita","last_name":"Peat","email":"tpeat41@photobucket.com","date_of_birth":"2018-03-09T21:57:41Z","age":49,"country":"Ukraine","phone":"278-709-1821"},
{"id":147,"first_name":"Leanna","last_name":"Heale","email":"lheale42@zdnet.com","date_of_birth":"1995-10-02T07:16:10Z","age":36,"country":"China","phone":"237-606-7162"},
{"id":148,"first_name":"Parke","last_name":"Lavallie","email":"plavallie43@alexa.com","date_of_birth":"1997-11-26T01:46:41Z","age":57,"country":"Ukraine","phone":"528-314-1483"},
{"id":149,"first_name":"Tracie","last_name":"Saiens","email":"tsaiens44@usgs.gov","date_of_birth":"1999-12-01T22:58:48Z","age":53,"country":"Portugal","phone":"553-590-6779"},
{"id":150,"first_name":"Elyn","last_name":"Slade","email":"eslade45@biglobe.ne.jp","date_of_birth":"2020-11-25T18:45:53Z","age":37,"country":"United States","phone":"914-924-1245"},
{"id":151,"first_name":"Moore","last_name":"Breston","email":"mbreston46@vk.com","date_of_birth":"1973-09-23T13:39:05Z","age":25,"country":"Portugal","phone":"785-631-6687"},
{"id":152,"first_name":"Carney","last_name":"Shrubsall","email":"cshrubsall47@weather.com","date_of_birth":"2004-03-08T13:41:55Z","age":57,"country":"Indonesia","phone":"338-882-5862"},
{"id":153,"first_name":"Hussein","last_name":"Beazley","email":"hbeazley48@weather.com","date_of_birth":"2004-07-10T18:16:35Z","age":52,"country":"Brazil","phone":"472-321-4092"},
{"id":154,"first_name":"Garrard","last_name":"Dionsetti","email":"gdionsetti49@pbs.org","date_of_birth":"2007-11-11T07:06:40Z","age":35,"country":"Indonesia","phone":"867-885-5466"},
{"id":155,"first_name":"Sybil","last_name":"Quarles","email":"squarles4a@infoseek.co.jp","date_of_birth":"2011-03-13T12:44:57Z","age":46,"country":"Indonesia","phone":"835-152-9048"},
{"id":156,"first_name":"Terrance","last_name":"Purdey","email":"tpurdey4b@multiply.com","date_of_birth":"2000-10-13T03:20:33Z","age":27,"country":"China","phone":"379-688-8971"},
{"id":157,"first_name":"Batsheva","last_name":"Monier","email":"bmonier4c@webs.com","date_of_birth":"2002-02-09T04:54:10Z","age":25,"country":"Sweden","phone":"187-901-3573"},
{"id":158,"first_name":"Bernardine","last_name":"Accomb","email":"baccomb4d@sciencedaily.com","date_of_birth":"2019-12-13T09:42:43Z","age":23,"country":"Peru","phone":"951-951-6749"},
{"id":159,"first_name":"Nalani","last_name":"Baalham","email":"nbaalham4e@washingtonpost.com","date_of_birth":"1974-02-28T12:03:35Z","age":26,"country":"China","phone":"705-993-9508"},
{"id":160,"first_name":"Danell","last_name":"Korfmann","email":"dkorfmann4f@timesonline.co.uk","date_of_birth":"2021-01-13T08:12:58Z","age":46,"country":"Indonesia","phone":"664-113-7409"},
{"id":161,"first_name":"Barri","last_name":"Dungate","email":"bdungate4g@sun.com","date_of_birth":"2003-10-31T10:24:24Z","age":21,"country":"Jamaica","phone":"599-624-5009"},
{"id":162,"first_name":"Alan","last_name":"Fellgett","email":"afellgett4h@flickr.com","date_of_birth":"2001-11-17T07:14:58Z","age":29,"country":"China","phone":"447-552-9295"},
{"id":163,"first_name":"Kristy","last_name":"Schrinel","email":"kschrinel4i@google.co.uk","date_of_birth":"1986-03-16T00:56:39Z","age":32,"country":"Nigeria","phone":"522-398-3124"},
{"id":164,"first_name":"Caroline","last_name":"Drayson","email":"cdrayson4j@cpanel.net","date_of_birth":"2021-01-13T14:15:08Z","age":25,"country":"Czech Republic","phone":"679-216-2589"},
{"id":165,"first_name":"Page","last_name":"Grichukhanov","email":"pgrichukhanov4k@auda.org.au","date_of_birth":"2011-12-18T08:31:01Z","age":25,"country":"Bulgaria","phone":"443-487-1569"},
{"id":166,"first_name":"Anabal","last_name":"Deerr","email":"adeerr4l@disqus.com","date_of_birth":"2022-02-19T05:55:00Z","age":40,"country":"Portugal","phone":"723-676-4285"},
{"id":167,"first_name":"Rubi","last_name":"Jopson","email":"rjopson4m@samsung.com","date_of_birth":"2014-06-19T18:24:30Z","age":49,"country":"Sudan","phone":"611-154-3033"},
{"id":168,"first_name":"Rayshell","last_name":"Lehr","email":"rlehr4n@noaa.gov","date_of_birth":"2011-12-18T18:31:26Z","age":53,"country":"China","phone":"857-507-5570"},
{"id":169,"first_name":"Dalia","last_name":"Rickell","email":"drickell4o@miitbeian.gov.cn","date_of_birth":"1981-07-05T09:44:50Z","age":18,"country":"Portugal","phone":"824-411-0114"},
{"id":170,"first_name":"Karlie","last_name":"Dragon","email":"kdragon4p@mlb.com","date_of_birth":"2019-10-17T00:26:45Z","age":49,"country":"Ukraine","phone":"680-963-0935"},
{"id":171,"first_name":"Salvidor","last_name":"Donaho","email":"sdonaho4q@lulu.com","date_of_birth":"1994-09-20T00:49:44Z","age":36,"country":"China","phone":"489-207-3115"},
{"id":172,"first_name":"Isabella","last_name":"Osgorby","email":"iosgorby4r@noaa.gov","date_of_birth":"1983-09-07T07:11:37Z","age":21,"country":"China","phone":"440-666-8296"},
{"id":173,"first_name":"Humfried","last_name":"Sommerland","email":"hsommerland4s@sourceforge.net","date_of_birth":"1979-02-21T10:17:12Z","age":31,"country":"Zimbabwe","phone":"124-310-6994"},
{"id":174,"first_name":"Kingsly","last_name":"Rubertelli","email":"krubertelli4t@yandex.ru","date_of_birth":"2013-02-28T11:35:28Z","age":26,"country":"Norway","phone":"731-437-5149"},
{"id":175,"first_name":"Tamma","last_name":"Terrey","email":"tterrey4u@biglobe.ne.jp","date_of_birth":"1993-07-12T10:48:30Z","age":45,"country":"France","phone":"906-865-9639"},
{"id":176,"first_name":"Vittoria","last_name":"Dufer","email":"vdufer4v@yahoo.com","date_of_birth":"1994-09-11T19:06:34Z","age":41,"country":"Portugal","phone":"549-777-8380"},
{"id":177,"first_name":"Mannie","last_name":"Ferry","email":"mferry4w@paginegialle.it","date_of_birth":"1994-07-09T02:19:16Z","age":26,"country":"China","phone":"996-864-0600"},
{"id":178,"first_name":"Donetta","last_name":"Skewes","email":"dskewes4x@over-blog.com","date_of_birth":"1973-02-13T00:46:09Z","age":47,"country":"United States","phone":"267-328-0080"},
{"id":179,"first_name":"Toby","last_name":"Garoghan","email":"tgaroghan4y@hexun.com","date_of_birth":"2016-04-16T12:16:56Z","age":22,"country":"Venezuela","phone":"781-947-3979"},
{"id":180,"first_name":"Kylie","last_name":"Ellesmere","email":"kellesmere4z@opensource.org","date_of_birth":"2015-10-13T19:00:23Z","age":37,"country":"China","phone":"106-244-0184"},
{"id":181,"first_name":"Kacy","last_name":"Surmeir","email":"ksurmeir50@xinhuanet.com","date_of_birth":"1980-08-14T17:45:39Z","age":42,"country":"Russia","phone":"746-136-9956"},
{"id":182,"first_name":"Brett","last_name":"M'Barron","email":"bmbarron51@nps.gov","date_of_birth":"1993-09-25T20:56:44Z","age":18,"country":"Philippines","phone":"877-275-4552"},
{"id":183,"first_name":"Diarmid","last_name":"Pinel","email":"dpinel52@wp.com","date_of_birth":"2011-12-28T12:25:38Z","age":32,"country":"China","phone":"487-520-7886"},
{"id":184,"first_name":"Sydney","last_name":"Blevin","email":"sblevin53@businesswire.com","date_of_birth":"2021-03-23T01:55:40Z","age":41,"country":"South Africa","phone":"507-690-7948"},
{"id":185,"first_name":"Phillipe","last_name":"Tuddenham","email":"ptuddenham54@businesswire.com","date_of_birth":"1983-07-02T23:31:48Z","age":23,"country":"United States","phone":"920-389-3099"},
{"id":186,"first_name":"Sacha","last_name":"Trudgian","email":"strudgian55@reverbnation.com","date_of_birth":"2002-04-27T23:23:03Z","age":19,"country":"Indonesia","phone":"658-545-8022"},
{"id":187,"first_name":"Mylo","last_name":"Ends","email":"mends56@intel.com","date_of_birth":"2023-04-23T03:59:57Z","age":31,"country":"Panama","phone":"408-342-3077"},
{"id":188,"first_name":"Cassandra","last_name":"Haug","email":"chaug57@people.com.cn","date_of_birth":"2004-02-13T22:14:16Z","age":20,"country":"Czech Republic","phone":"829-345-0979"},
{"id":189,"first_name":"Forster","last_name":"Summerskill","email":"fsummerskill58@theglobeandmail.com","date_of_birth":"1984-10-06T00:37:32Z","age":46,"country":"Kazakhstan","phone":"963-112-8830"},
{"id":190,"first_name":"Federico","last_name":"Outhwaite","email":"fouthwaite59@cam.ac.uk","date_of_birth":"1998-10-10T09:28:34Z","age":53,"country":"Ecuador","phone":"687-503-3163"},
{"id":191,"first_name":"Leyla","last_name":"Parsonage","email":"lparsonage5a@amazon.com","date_of_birth":"1972-03-08T20:47:51Z","age":57,"country":"Czech Republic","phone":"102-307-1306"},
{"id":192,"first_name":"Giacomo","last_name":"Storck","email":"gstorck5b@themeforest.net","date_of_birth":"1993-04-16T22:54:32Z","age":18,"country":"Indonesia","phone":"512-198-5835"},
{"id":193,"first_name":"Benedikt","last_name":"Alston","email":"balston5c@google.de","date_of_birth":"1985-05-26T10:09:51Z","age":38,"country":"Saint Lucia","phone":"339-502-6704"},
{"id":194,"first_name":"Niccolo","last_name":"Trowsdall","email":"ntrowsdall5d@tamu.edu","date_of_birth":"2013-10-31T14:15:20Z","age":49,"country":"Philippines","phone":"363-402-0074"},
{"id":195,"first_name":"Rici","last_name":"Joskowicz","email":"rjoskowicz5e@spotify.com","date_of_birth":"2013-09-08T06:03:03Z","age":57,"country":"Indonesia","phone":"946-241-7174"},
{"id":196,"first_name":"Elvis","last_name":"Slopier","email":"eslopier5f@aboutads.info","date_of_birth":"1995-09-15T08:51:30Z","age":56,"country":"China","phone":"394-996-0501"},
{"id":197,"first_name":"Suki","last_name":"Grassick","email":"sgrassick5g@amazon.co.uk","date_of_birth":"1995-01-29T06:21:40Z","age":26,"country":"China","phone":"614-510-2571"},
{"id":198,"first_name":"Cesar","last_name":"Kornel","email":"ckornel5h@japanpost.jp","date_of_birth":"2017-02-18T16:04:07Z","age":43,"country":"Indonesia","phone":"137-945-2663"},
{"id":199,"first_name":"Silvie","last_name":"Swalwel","email":"sswalwel5i@ocn.ne.jp","date_of_birth":"1975-05-09T14:51:32Z","age":57,"country":"Argentina","phone":"965-206-2845"},
{"id":200,"first_name":"Debby","last_name":"Bukac","email":"dbukac5j@wikipedia.org","date_of_birth":"2022-08-14T07:23:26Z","age":53,"country":"Guatemala","phone":"231-467-1352"}]